rumboost/__init__.py
rumboost/dataset.py
rumboost/models.py
rumboost/post_process.py
rumboost/rumboost.py
rumboost/utility_plotting.py
rumboost/utility_smoothing.py
rumboost/utils.py
rumboost-1.0.2.dist-info/LICENSE.txt
rumboost-1.0.2.dist-info/METADATA
rumboost-1.0.2.dist-info/WHEEL
rumboost-1.0.2.dist-info/top_level.txt
rumboost-1.0.2.dist-info/RECORD
