Metadata-Version: 2.1
Name: rumboost
Version: 1.0.2
Summary: Gradient Boosting Decision Trees for Random Utility Models
Home-page: https://github.com/NicoSlvd/rumboost
Author: Nicolas Salvadé, Tim Hillel
Author-email: Nicolas Salvadé <nicolas.salvade.22@ucl.ac.uk>
Project-URL: Homepage, https://github.com/NicoSlvd/rumboost
Project-URL: Issues, https://github.com/NicoSlvd/rumboost/issues
Classifier: Programming Language :: Python :: 3
Classifier: License :: OSI Approved :: MIT License
Classifier: Operating System :: OS Independent
Requires-Python: >=3.11
License-File: LICENSE.txt
Requires-Dist: biogeme ==3.2.11
Requires-Dist: hyperopt ==0.2.7
Requires-Dist: lightgbm ==3.3.5
Requires-Dist: matplotlib ==3.7.1
Requires-Dist: numpy ==1.24.3
Requires-Dist: pandas ==2.0.2
Requires-Dist: scikit-learn ==1.2.2
Requires-Dist: scipy ==1.10.1
Requires-Dist: seaborn ==0.12.2
